ask_james/__init__.py
ask_james/__main__.py
ask_james/server.py
ask_james-0.1.1.dist-info/licenses/LICENSE
ask_james-0.1.1.dist-info/METADATA
ask_james-0.1.1.dist-info/WHEEL
ask_james-0.1.1.dist-info/entry_points.txt
ask_james-0.1.1.dist-info/top_level.txt
ask_james-0.1.1.dist-info/RECORD
