Metadata-Version: 2.4
Name: ask-james
Version: 0.1.1
Summary: Model Context Protocol server that offers a 'James' second-opinion review tool.
Author-email: Corneliu <cornel.croitoru@gmail.com>
Requires-Python: >=3.11
License-File: LICENSE
Requires-Dist: mcp>=0.3.0
Requires-Dist: litellm>=1.42.0
Requires-Dist: pydantic>=2.7.0
Dynamic: license-file
